perfpy/__init__.py
perfpy/picking_data_model/__init__.py
perfpy/picking_data_model/using_attrs.py
perfpy/picking_data_model/using_dicts.py
perfpy/picking_data_model/using_named_tuples.py
perfpy/picking_data_model/using_pydantic.py
self_py-0.0.1a0.dist-info/LICENSE
self_py-0.0.1a0.dist-info/METADATA
self_py-0.0.1a0.dist-info/WHEEL
self_py-0.0.1a0.dist-info/entry_points.txt
self_py-0.0.1a0.dist-info/top_level.txt
self_py-0.0.1a0.dist-info/RECORD
