Metadata-Version: 2.1
Name: self-py
Version: 0.0.1a0
Summary: Understanding performance characteristics of common python constructs
Home-page: https://github.com/mr-uuid/perfpy
Author: Omar Eid
Author-email: contact.omar.eid@gmail.com
License: UNKNOWN
Platform: any
Classifier: Development Status :: 4 - Beta
Classifier: Intended Audience :: Developers
Classifier: License :: OSI Approved :: GNU General Public License (GPL)
Classifier: Operating System :: POSIX
Classifier: Programming Language :: Python
Classifier: Topic :: Software Development :: Libraries
Requires-Dist: attrs
Requires-Dist: pydantic
Requires-Dist: toolz
Requires-Dist: numpy
Provides-Extra: dev
Requires-Dist: ipython ; extra == 'dev'
Requires-Dist: mypy ; extra == 'dev'
Requires-Dist: pytest ; extra == 'dev'
Requires-Dist: pytest-pep8 ; extra == 'dev'
Requires-Dist: pytest-profiling ; extra == 'dev'
Requires-Dist: pstats-view ; extra == 'dev'
Requires-Dist: flake8 ; extra == 'dev'
